danav/__init__.py
danav-0.0.1.dist-info/LICENSE
danav-0.0.1.dist-info/METADATA
danav-0.0.1.dist-info/WHEEL
danav-0.0.1.dist-info/top_level.txt
danav-0.0.1.dist-info/RECORD
