Metadata-Version: 2.1
Name: danav
Version: 0.0.1
Summary: danav
Author: abhishek
Project-URL: Homepage, https://github.com/abhishekkrthakur/danav
Project-URL: Issues, https://github.com/abhishekkrthakur/danav/issues
Keywords: danav
Classifier: Development Status :: 5 - Production/Stable
Classifier: License :: OSI Approved :: Apache Software License
Classifier: Operating System :: OS Independent
Classifier: Programming Language :: Python :: 3.10
Classifier: Programming Language :: Python :: 3.11
Classifier: Topic :: Scientific/Engineering :: Artificial Intelligence
License-File: LICENSE
